{
  "name": "Augmetic Engine-Plate",
  "type": "armour",
  "img": "icons/svg/shield.svg",
  "system": {
    "type": "power",
    "weight": 20,
    "availability": "rare",
    "notes": "Environmentally Sealed, gives +30 to resist extreme environmental conditions and has 8 hours of air. Contains internal vox, mag-boots, and photo-visor. -10 to Agility and Further -10 for tests requiring fine manipulation using the gauntlets. Counts as AP 10 vs Flame/Energy weapons.",
    "source": "RT: Hostile Acquisitions",
    "description": {
      "value": "<p>Environmentally Sealed, gives +30 to resist extreme environmental conditions and has 8 hours of air. Contains internal vox, mag-boots, and photo-visor. -10 to Agility and Further -10 for tests requiring fine manipulation using the gauntlets. Counts as AP 10 vs Flame/Energy weapons.</p>"
    },
    "modificationSlots": 2,
    "coverage": [
      "all"
    ],
    "armourPoints": {
      "head": 7,
      "body": 7,
      "leftArm": 7,
      "rightArm": 7,
      "leftLeg": 7,
      "rightLeg": 7
    },
    "modifications": [],
    "maxAgility": null,
    "properties": []
  },
  "effects": [],
  "flags": {},
  "_id": "0Nu5BOjjY4Mm0D0I"
}
