{
  "name": "Cypra-Pattern Class 1 Drive",
  "type": "shipComponent",
  "img": "icons/svg/gears.svg",
  "system": {
    "type": "(es.) Plasma Drive (Archeotech)",
    "hullType": "Transports",
    "powerUsage": -30,
    "spaceUsage": 10,
    "spCost": 2,
    "effect": "Generates Power rather than using it. +15 to Silent Running Manoeuvers. -15 to Attempts to detect this vessel (actions that use ship Detection, such as Active Augury).",
    "availability": "Extremely Rare",
    "source": "RT: BF Koronus",
    "description": {
      "value": "<p>Generates Power rather than using it. +15 to Silent Running Manoeuvers. -15 to Attempts to detect this vessel (actions that use ship Detection, such as Active Augury).</p>"
    }
  },
  "effects": [],
  "flags": {},
  "_id": "ILCNJeWMODDmepfX"
}