{
  "name": "Mimic Engine (Cruiser)",
  "type": "shipComponent",
  "img": "icons/svg/gears.svg",
  "system": {
    "type": "(es.) Plasma Drive (Xenotech)",
    "hullType": "Cruisers",
    "powerUsage": -75,
    "spaceUsage": 14,
    "spCost": 3,
    "effect": "Generates power rather than using it. The Ship's Navigator can make +10 Perception Test on the bridge to modify mimicry to any vessel previously encounted via a bone-like node mounted on the bridge. The ship appears as that vessel to long-range sensors, although the illusion is broken once creacing visual contact.",
    "availability": "near-unique",
    "source": "RT: Hostile Acquisitions",
    "description": {
      "value": "<p>Generates power rather than using it. The Ship's Navigator can make +10 Perception Test on the bridge to modify mimicry to any vessel previously encounted via a bone-like node mounted on the bridge. The ship appears as that vessel to long-range sensors, although the illusion is broken once creacing visual contact.</p>"
    },
    "modifiers": {
      "speed": 0,
      "manoeuvrability": 0,
      "detection": 0,
      "armour": 0,
      "hullIntegrity": 0,
      "turretRating": 0
    }
  },
  "effects": [],
  "flags": {},
  "_id": "oOOWdM2qu63v3jxi"
}
