{
  "name": "Greed is Good",
  "type": "talent",
  "img": "icons/svg/target.svg",
  "system": {
    "category": "Talent",
    "requirements": "Kroot, Mercenary Trait",
    "effect": "The character can reroll any failed Willpower Test to avoid Fear and Pinning",
    "source": "RT: Into the Storm",
    "description": {
      "value": "<p>The character can reroll any failed Willpower Test to avoid Fear and Pinning</p>"
    },
    "modifiers": {
      "characteristics": {},
      "skills": {},
      "combat": {},
      "other": []
    },
    "isPassive": true,
    "isRollable": true,
    "tier": 1,
    "benefit": "",
    "aptitudes": []
  },
  "effects": [],
  "flags": {},
  "_id": "QZQNiGIrX0OZdDWK"
}