{
  "name": "Improved Dexterity",
  "type": "talent",
  "img": "icons/svg/target.svg",
  "system": {
    "category": "combat",
    "source": "OW: Shield of Humanity",
    "description": {
      "value": "<p>The Ogryn can wield Basic and Thrown Ranged Weapons, as well as Melee Weapons that do not have the Ogryn-Proof Trait as if they did not have the Clumsy Trait. Any of these weapons that would require Two Hands do not when wielded by this Ogryn.</p>"
    },
    "tier": 1,
    "benefit": "<p>The Ogryn can wield Basic and Thrown Ranged Weapons, as well as Melee Weapons that do not have the Ogryn-Proof Trait as if they did not have the Clumsy Trait. Any of these weapons that would require Two Hands do not when wielded by this Ogryn.</p>",
    "aptitudes": [],
    "prerequisites": {
      "text": "Bone 'Ead Advanced Specialty (300xp)",
      "characteristics": {},
      "skills": [],
      "talents": []
    },
    "cost": 300,
    "isPassive": true
  },
  "effects": [],
  "flags": {},
  "_id": "lXoP5NqER9XaieCJ"
}
