{
  "name": "Hand Cannon (Stormchild)",
  "type": "weapon",
  "img": "icons/svg/sword.svg",
  "system": {
    "class": "Pistol",
    "type": "SP",
    "range": "35m",
    "rof": "S/-/-",
    "damage": "1d10+4",
    "damageType": "Impact",
    "penetration": 2,
    "clip": 5,
    "reload": "2 Full",
    "special": null,
    "weight": "3kg",
    "availability": "Average",
    "cost": "65 T",
    "source": "DH: Inquisitor's Handbook",
    "note": null,
    "description": {
      "value": ""
    }
  },
  "effects": [],
  "flags": {},
  "_id": "TW3ukAfJbGeBF0wR"
}