{
  "name": "Legion Chainfist",
  "type": "weapon",
  "img": "icons/svg/sword.svg",
  "system": {
    "class": "Melee",
    "type": "Power",
    "range": "-",
    "rof": "-",
    "damage": "2d10",
    "damageType": "Energy",
    "penetration": 10,
    "clip": "-",
    "reload": "-",
    "special": "Power Field, Tearing, Unwieldy,  SM Wep",
    "weight": "48kg",
    "availability": "Extremely Rare",
    "cost": "-",
    "source": "Black Crusade: Core",
    "note": "Chaos Legionary Weapon. Dangerous to own. Can only be used whilst wearing Terminator Armour or some equally bulky equivilent. Doubles Strength Bonus. Attached to a bulky gauntlet which can only be used for basic manipulation (couldn't use a weapon or write, but could pick something up)",
    "description": {
      "value": "<p><b>Special:</b> Power Field, Tearing, Unwieldy,  SM Wep</p><p><b>Note:</b> Chaos Legionary Weapon. Dangerous to own. Can only be used whilst wearing Terminator Armour or some equally bulky equivilent. Doubles Strength Bonus. Attached to a bulky gauntlet which can only be used for basic manipulation (couldn't use a weapon or write, but could pick something up)</p>"
    },
    "damageFormula": "2d10",
    "craftsmanshipMods": {
      "toHit": 0,
      "damage": 0,
      "penetration": 0
    }
  },
  "effects": [],
  "flags": {},
  "_id": "xacJ2kdZhVH57RXL"
}