{
  "name": "Tau Longshot Pulse Rifle",
  "type": "weapon",
  "img": "icons/svg/sword.svg",
  "system": {
    "identifier": "tau-longshot-pulse-rifle",
    "class": "basic",
    "type": "exotic",
    "twoHanded": false,
    "melee": false,
    "attack": {
      "type": "ranged",
      "characteristic": "ballisticSkill",
      "modifier": 0,
      "range": {
        "value": 200,
        "units": "m",
        "special": ""
      },
      "rateOfFire": {
        "single": true,
        "semi": 2,
        "full": 0
      }
    },
    "damage": {
      "formula": "2d10",
      "type": "energy",
      "bonus": 3,
      "penetration": 4
    },
    "special": [
      "accurate",
      "tearing"
    ],
    "clip": {
      "max": 12,
      "value": 12,
      "type": ""
    },
    "reload": "2-full",
    "weight": 8,
    "availability": "near-unique",
    "craftsmanship": "common",
    "quantity": 1,
    "cost": {
      "value": 0,
      "currency": "throne"
    },
    "equipped": false,
    "stowed": false,
    "container": "",
    "description": {
      "value": "<p><b>Special:</b> Accurate, Tearing</p><p><b>Note:</b> Up to +20 to Acquisition Tests if acquired through a friendly Tau Settlement.</p>"
    },
    "modifications": [],
    "proficiency": "",
    "notes": "Up to +20 to Acquisition Tests if acquired through a friendly Tau Settlement.",
    "source": "RT: Tau Char. Guide"
  },
  "effects": [],
  "flags": {},
  "_id": "mBSgBTspZFPkj7s3"
}