{
  "name": "Vivisector",
  "type": "weapon",
  "img": "icons/svg/sword.svg",
  "system": {
    "class": "Melee",
    "type": "Exotic",
    "range": "-",
    "rof": "-",
    "damage": "1d5+5",
    "damageType": "Rending",
    "penetration": 0,
    "clip": "-",
    "reload": "-",
    "special": "Tearing, Unwieldy",
    "weight": "1.5kg",
    "availability": "Rare",
    "cost": "650 T",
    "source": "DH: Inquisitor's Handbook",
    "note": "Grants +10 to Interrogation and Intimidation Tests. As well as +10 to medicae tests to repair servitors or conduct an Autopsy.\nCan be fitted with a injector rigs for 500 Thrones (or +1 Rarity) to add Toxic Quality.",
    "description": {
      "value": "<p><b>Special:</b> Tearing, Unwieldy</p><p><b>Note:</b> Grants +10 to Interrogation and Intimidation Tests. As well as +10 to medicae tests to repair servitors or conduct an Autopsy.\nCan be fitted with a injector rigs for 500 Thrones (or +1 Rarity) to add Toxic Quality.</p>"
    }
  },
  "effects": [],
  "flags": {},
  "_id": "CfHiFuuDQuEQVnKz"
}