{
  "name": "Quarantine World",
  "type": "originPath",
  "img": "systems/wh40k-rpg/icons/talents/blue/b_26.png",
  "system": {
    "identifier": "quarantine-world",
    "step": "homeworld",
    "stepIndex": 1,
    "description": {
      "value": "<h2>Quarantine World</h2><p>Quarantine worlds are sealed by Imperial writ because whatever lies on their surface is judged too dangerous to risk spreading beyond it. Those who escape such places live on borrowed time, and quickly learn to hide who they are, what they know, and where they came from. That secrecy translates well to an Inquisitorial warband, where keeping truths buried can be as important as uncovering them.</p><h3>Homeworld Bonus</h3><p>+Ballistic Skill, +Intelligence, -Strength</p><h3>Homeworld Aptitude</h3><p>Fieldcraft</p><h3>Wounds</h3><p>8+1d5</p><h3>Fate Threshold</h3><p>3 (Emperor's Blessing 9+)</p><h3>Homeworld Trait</h3><p><strong>Secretive by Nature:</strong> Whenever the warband's Subtlety would decrease, it decreases by 2 less, to a minimum reduction of 1.</p>"
    },
    "requirements": {
      "text": "Origin Path: Homeworld",
      "previousSteps": [],
      "excludedSteps": []
    },
    "grants": {
      "woundsFormula": "8+1d5",
      "wounds": 0,
      "fateFormula": "",
      "fateThreshold": 3,
      "blessedByEmperor": false,
      "skills": [],
      "talents": [],
      "traits": [],
      "aptitudes": [
        "Fieldcraft"
      ],
      "equipment": [],
      "specialAbilities": [
        {
          "name": "Secretive by Nature",
          "description": "Whenever the warband's Subtlety would decrease, it decreases by 2 less, to a minimum reduction of 1."
        }
      ],
      "choices": []
    },
    "modifiers": {
      "characteristics": {
        "ballisticSkill": 5,
        "intelligence": 5
      },
      "skills": {},
      "combat": {},
      "resources": {
        "wounds": 0,
        "fate": 0,
        "insanity": 0,
        "corruption": 0
      },
      "other": [
        {
          "name": "Strength",
          "value": -5
        }
      ],
      "situational": {
        "characteristics": [],
        "skills": [],
        "combat": []
      }
    },
    "effectText": "",
    "notes": "Emperor's Blessing: On a roll of 9+ on 1d10, the character begins with an extra Fate Point.",
    "selectedChoices": {},
    "activeModifiers": [],
    "positions": []
  },
  "effects": [],
  "flags": {},
  "_id": "EB2QrnWld000006A"
}
