{
  "name": "Servo-Manipulators",
  "type": "armourCustomisation",
  "img": "icons/svg/upgrade.svg",
  "system": {
    "armourTypes": "Any armour that imposes penalties to agility tests or fine manipulation tests.",
    "effect": "Removes penalties to fine manipulation caused by armour.",
    "weight": "+1kg",
    "availability": "Rare",
    "source": "RT: Hostile Acq.",
    "description": {
      "value": "<p>Removes penalties to fine manipulation caused by armour.</p>"
    }
  },
  "effects": [],
  "flags": {},
  "_id": "WylqFeKG3uewIuxb"
}