{
  "name": "Bionic Arm",
  "type": "cybernetic",
  "img": "icons/svg/gears.svg",
  "system": {
    "weight": 0,
    "availability": "scarce",
    "craftsmanship": "common",
    "cost": {
      "value": 1000,
      "currency": "throne"
    },
    "quantity": 1,
    "description": {
      "value": "<p>A common craftsmanship bionic arm replaces a normal arm in all functionality. Poor craftsmanship arms impose a -5 penalty to Weapon Skill and Ballistic Skill tests made with that arm. Good craftsmanship arms grant a +10 bonus to Agility tests involving delicate manipulation. Best craftsmanship arms grant a +10 bonus to Strength tests using the arm and can store small items such as pistol clips.</p><p>Damage works as normal, although inappropriate effects like bleeding simply render the limb useless.</p>",
      "chat": "",
      "summary": "A bionic arm replaces a normal arm in all functionality, with craftsmanship affecting its performance."
    },
    "source": {
      "book": "DH2e Core",
      "page": "",
      "custom": ""
    },
    "equipped": true,
    "effect": "A bionic arm replaces a normal arm in all functionality, with craftsmanship affecting its performance.",
    "notes": "",
    "identifier": "bionic-arm",
    "gameSystems": [
      "dh2e"
    ],
    "type": "implant",
    "locations": [
      "body"
    ],
    "hasArmourPoints": false,
    "armourPoints": {
      "head": 0,
      "leftArm": 0,
      "rightArm": 0,
      "body": 0,
      "leftLeg": 0,
      "rightLeg": 0
    },
    "drawbacks": "<p>Requires implantation surgery and appropriate maintenance.</p>",
    "installation": {
      "surgery": "Major surgery required",
      "difficulty": "-10 Medicae",
      "recoveryTime": "1 week"
    },
    "modifiers": {
      "characteristics": {},
      "skills": {},
      "combat": {},
      "resources": {},
      "other": []
    }
  },
  "effects": [],
  "flags": {},
  "_id": "189lffewjxeei000"
}
